tanager_tcp/__init__.py
tanager_tcp-0.0.12.dist-info/METADATA
tanager_tcp-0.0.12.dist-info/WHEEL
tanager_tcp-0.0.12.dist-info/top_level.txt
tanager_tcp-0.0.12.dist-info/RECORD
